setup.py
tests/__init__.py
tests/base.py
tests/test_memcache_storage.py
thumbor_memcached/__init__.py
thumbor_memcached/storage.py
thumbor_memcached/version.py
thumbor_memcached.egg-info/PKG-INFO
thumbor_memcached.egg-info/SOURCES.txt
thumbor_memcached.egg-info/dependency_links.txt
thumbor_memcached.egg-info/entry_points.txt
thumbor_memcached.egg-info/requires.txt
thumbor_memcached.egg-info/top_level.txt