Metadata-Version: 1.1
Name: thumbor-memcached
Version: 5.1.0
Summary: thumbor-memcached provides storages using memcached as a backend.
Home-page: https://github.com/thumbor-community/thumbor-memcached
Author: Bernardo Heynemann
Author-email: heynemann@gmail.com
License: MIT
Keywords: memcache memcached thumbor storage
Platform: UNKNOWN
Classifier: Development Status :: 4 - Beta
Classifier: Intended Audience :: Developers
Classifier: License :: OSI Approved :: MIT License
Classifier: Natural Language :: English
Classifier: Operating System :: Unix
Classifier: Programming Language :: Python :: 2.7
Classifier: Programming Language :: Python :: 3.4
Classifier: Programming Language :: Python :: Implementation :: PyPy
Classifier: Operating System :: OS Independent
